thingbits_ha/__init__.py
thingbits_ha-0.1.0.dist-info/METADATA
thingbits_ha-0.1.0.dist-info/WHEEL
thingbits_ha-0.1.0.dist-info/top_level.txt
thingbits_ha-0.1.0.dist-info/RECORD
